causica/__init__.py
causica/config/lightning/default_data.yaml
causica/config/lightning/default_gaussian.yaml
causica/config/lightning/default_spline.yaml
causica/data_generation/__init__.py
causica/data_generation/generate_data.py
causica/data_generation/samplers/__init__.py
causica/data_generation/samplers/functional_relationships_sampler.py
causica/data_generation/samplers/noise_dist_sampler.py
causica/data_generation/samplers/sampler.py
causica/data_generation/samplers/sem_sampler.py
causica/datasets/__init__.py
causica/datasets/causal_dataset.py
causica/datasets/causica_dataset_format/__init__.py
causica/datasets/causica_dataset_format/load.py
causica/datasets/causica_dataset_format/save.py
causica/datasets/interventional_data.py
causica/datasets/loaded_expert_graph_container.py
causica/datasets/normalization.py
causica/datasets/samplers.py
causica/datasets/synthetic_dataset.py
causica/datasets/tensordict_utils.py
causica/datasets/timeseries_dataset.py
causica/datasets/variable_types.py
causica/distributions/__init__.py
causica/distributions/adjacency/__init__.py
causica/distributions/adjacency/adjacency_distributions.py
causica/distributions/adjacency/constrained_adjacency_distributions.py
causica/distributions/adjacency/edges_per_node_erdos_renyi.py
causica/distributions/adjacency/enco.py
causica/distributions/adjacency/erdos_renyi.py
causica/distributions/adjacency/fixed_adjacency_distribution.py
causica/distributions/adjacency/geometric_random_graph.py
causica/distributions/adjacency/gibbs_dag_prior.py
causica/distributions/adjacency/scale_free.py
causica/distributions/adjacency/stochastic_block_model.py
causica/distributions/adjacency/temporal_adjacency_distributions.py
causica/distributions/adjacency/three_way.py
causica/distributions/adjacency/watts_strogatz.py
causica/distributions/distribution_module.py
causica/distributions/gumbel_binary.py
causica/distributions/noise/__init__.py
causica/distributions/noise/bernoulli.py
causica-0.4.5.dist-info/LICENSE
causica-0.4.5.dist-info/METADATA
causica-0.4.5.dist-info/WHEEL
causica-0.4.5.dist-info/RECORD
