Metadata-Version: 2.1
Name: causica
Version: 0.4.5
Summary: 
License: MIT
Author: Microsoft Research - Causica
Requires-Python: >=3.10,<3.11
Classifier: License :: OSI Approved :: MIT License
Classifier: Programming Language :: Python :: 3
Classifier: Programming Language :: Python :: 3.10
Provides-Extra: seaborn
Requires-Dist: azureml-mlflow (>=1.46.0,<2.0.0)
Requires-Dist: dataclasses-json (>=0.5.7,<0.6.0)
Requires-Dist: igraph (>=0.11.3,<0.12.0)
Requires-Dist: jsonargparse (<4.21.0)
Requires-Dist: mlflow (>=2.0.0,<3.0.0)
Requires-Dist: numpy (>=1.22.4,<2.0.0)
Requires-Dist: pandas (>=1.4.2,<2.0.0)
Requires-Dist: pytorch-lightning[extra] (>=2.1.0,<3.0.0)
Requires-Dist: seaborn (>=0.12.2,<0.13.0) ; extra == "seaborn"
Requires-Dist: tensorboard (>=2.9.0,<3.0.0)
Requires-Dist: tensordict (>=0.1.0,<0.2.0)
Requires-Dist: torch (==2.0.0)
Requires-Dist: torchmetrics (>=1.0.3,<2.0.0)
Requires-Dist: types-PyYAML (>=6.0.12.2,<7.0.0.0)
